COPYRIGHT
MANIFEST.in
ORDF.n3
README.txt
README_LAYERCAKE.txt
pip-requirements.txt
setup.cfg
setup.py
docs/administration.rst
docs/api_docs.rst
docs/cmdline.rst
docs/design_considerations.rst
docs/distribution.rst
docs/graphs.rst
docs/index.rst
docs/message_handling.rst
docs/miscellaneous.rst
docs/namespaces.rst
docs/notation3.rst
docs/odm.rst
docs/ordf_handler.rst
docs/ordf_handler_fuxi.rst
docs/ordf_handler_pt.rst
docs/ordf_handler_queue.rst
docs/ordf_handler_rdf.rst
docs/ordf_handler_xapian.rst
docs/ordf_pylons_controllers.rst
docs/ordf_pylons_serialiser.rst
docs/ordf_vocab_changeset.rst
docs/ordf_vocab_foaf.rst
docs/ordf_vocab_fresnel.rst
docs/ordf_vocab_opencyc.rst
docs/ordf_vocab_opmv.rst
docs/ordf_vocab_ore.rst
docs/pylons_support.rst
docs/vocabulary.rst
examples/cmdline.ini
examples/fourstore.ini
examples/fresnel.ini
examples/fuxi.ini
examples/noqueue.ini
examples/pairtree.ini
examples/pylons.ini
examples/simple.ini
examples/xapian.ini
ordf/__init__.py
ordf/collection.py
ordf/command.py
ordf/graph.py
ordf/namespace.py
ordf/rdfobj.py
ordf/serializer.py
ordf/term.py
ordf/utils.py
ordf.egg-info/PKG-INFO
ordf.egg-info/SOURCES.txt
ordf.egg-info/dependency_links.txt
ordf.egg-info/entry_points.txt
ordf.egg-info/not-zip-safe
ordf.egg-info/requires.txt
ordf.egg-info/top_level.txt
ordf/handler/__init__.py
ordf/handler/cache.py
ordf/handler/fuxi.py
ordf/handler/pt.py
ordf/handler/queue.py
ordf/handler/rdf.py
ordf/handler/xap.py
ordf/pylons/__init__.py
ordf/pylons/proxy.py
ordf/pylons/serialiser.py
ordf/pylons/xap.py
ordf/rules/ordf_rules.n3
ordf/rules/pD-rules.n3
ordf/tests/__init__.py
ordf/tests/test_cs.py
ordf/tests/test_fresnel.py
ordf/tests/test_fuxi.py
ordf/tests/test_graph.py
ordf/tests/test_handler.py
ordf/tests/test_obj.py
ordf/tests/test_opmv.py
ordf/tests/test_owl.py
ordf/tests/test_pt.py
ordf/tests/test_queue.py
ordf/tests/test_rdflib.py
ordf/tests/test_skos.py
ordf/tests/data/card.rdf
ordf/tests/data/lens.n3
ordf/tests/data/marc.n3
ordf/tests/data/marc_bio.n3
ordf/tests/data/test.rdf
ordf/vocab/__init__.py
ordf/vocab/bibo.py
ordf/vocab/changeset.py
ordf/vocab/foaf.py
ordf/vocab/fresnel.py
ordf/vocab/opencyc.py
ordf/vocab/opmv.py
ordf/vocab/ore.py
