Metadata-Version: 1.0
Name: ordf
Version: 0.21
Summary: Open Knowledge Foundation RDF
Home-page: http://ordf.org/
Author: Open Knowledge Foundation
Author-email: okfn-help@lists.okfn.org
License: AGPL
Keywords: rdf rdflib provenance messaging
Platform: UNKNOWN
Classifier: Development Status :: 3 - Alpha
Classifier: Environment :: Console
Classifier: Environment :: Web Environment
Classifier: Framework :: Paste
Classifier: Framework :: Pylons
Classifier: Intended Audience :: Developers
Classifier: Intended Audience :: Information Technology
Classifier: Intended Audience :: Science/Research
Classifier: License :: OSI Approved :: GNU Affero General Public License v3
Classifier: Operating System :: POSIX
Classifier: Programming Language :: Python :: 2.6
Classifier: Topic :: Internet
Classifier: Topic :: Scientific/Engineering :: Artificial Intelligence
Classifier: Topic :: Software Development :: Libraries :: Python Modules
